roci/.DS_Store
roci/__init__.py
roci/main.py
roci/structure/.github/workflows/main.yml
roci/structure/.gitignore
roci/structure/Makefile
roci/structure/README.md
roci/structure/docs/Makefile
roci/structure/docs/conf.py
roci/structure/docs/index.rst
roci/structure/docs/make.bat
roci/structure/requirements.txt
roci/structure/src/__init__.py
roci/structure/src/data/input.txt
roci/structure/src/day01.py
roci/structure/src/main.py
roci/structure/src/utils.py
roci/structure/tests/__init__.py
roci/structure/tests/test_week_one.py
roci-0.2.1.dist-info/entry_points.txt
roci-0.2.1.dist-info/WHEEL
roci-0.2.1.dist-info/METADATA
roci-0.2.1.dist-info/RECORD
